techsummly/__init__.py
techsummly/main.py
techsummly/prompts.py
techsummly-2025.12.21100854.dist-info/METADATA
techsummly-2025.12.21100854.dist-info/WHEEL
techsummly-2025.12.21100854.dist-info/top_level.txt
techsummly-2025.12.21100854.dist-info/RECORD
