Metadata-Version: 2.4
Name: techsummly
Version: 2025.12.21100854
Summary: A new package designed to facilitate structured and reliable interactions with language models for analyzing and summarizing technical discussions. Given a detailed description or excerpt of a technic
Author-email: techsummly <hi@eugene.plus>
License: MIT
Project-URL: Homepage, https://github.com/chigwell/techsummly
Requires-Python: >=3.9
Requires-Dist: langchain-llm7>=0.0.0
Requires-Dist: llmatch-messages>=0.0.0
Requires-Dist: langchain-core>=0.3.0
